legacy_tl_new-1.8.0.dist-info/licenses/LICENSE
legacytl/__init__.py
legacytl/custom.py
legacytl/functions.py
legacytl/helpers.py
legacytl/hints.py
legacytl/password.py
legacytl/requestiter.py
legacytl/sync.py
legacytl/types.py
legacytl/utils.py
legacytl/version.py
legacytl/_updates/__init__.py
legacytl/_updates/entitycache.py
legacytl/_updates/messagebox.py
legacytl/_updates/session.py
legacytl/client/__init__.py
legacytl/client/account.py
legacytl/client/auth.py
legacytl/client/bots.py
legacytl/client/buttons.py
legacytl/client/chats.py
legacytl/client/dialogs.py
legacytl/client/downloads.py
legacytl/client/messageparse.py
legacytl/client/messages.py
legacytl/client/telegrambaseclient.py
legacytl/client/telegramclient.py
legacytl/client/updates.py
legacytl/client/uploads.py
legacytl/client/users.py
legacytl/crypto/__init__.py
legacytl/crypto/aes.py
legacytl/crypto/aesctr.py
legacytl/crypto/authkey.py
legacytl/crypto/cdndecrypter.py
legacytl/crypto/factorization.py
legacytl/crypto/libssl.py
legacytl/crypto/rsa.py
legacytl/errors/__init__.py
legacytl/errors/common.py
legacytl/errors/rpcbaseerrors.py
legacytl/errors/rpcerrorlist.py
legacytl/events/__init__.py
legacytl/events/album.py
legacytl/events/callbackquery.py
legacytl/events/chataction.py
legacytl/events/common.py
legacytl/events/inlinequery.py
legacytl/events/messagedeleted.py
legacytl/events/messageedited.py
legacytl/events/messageread.py
legacytl/events/newmessage.py
legacytl/events/raw.py
legacytl/events/userupdate.py
legacytl/extensions/__init__.py
legacytl/extensions/binaryreader.py
legacytl/extensions/html.py
legacytl/extensions/markdown.py
legacytl/extensions/messagepacker.py
legacytl/network/__init__.py
legacytl/network/authenticator.py
legacytl/network/mtprotoplainsender.py
legacytl/network/mtprotosender.py
legacytl/network/mtprotostate.py
legacytl/network/requeststate.py
legacytl/network/connection/__init__.py
legacytl/network/connection/connection.py
legacytl/network/connection/http.py
legacytl/network/connection/tcpabridged.py
legacy_tl_new-1.8.0.dist-info/METADATA
legacy_tl_new-1.8.0.dist-info/WHEEL
legacy_tl_new-1.8.0.dist-info/top_level.txt
legacy_tl_new-1.8.0.dist-info/RECORD
