Metadata-Version: 2.4
Name: Legacy-TL-New
Version: 1.8.0
Summary: Full-featured Telegram client library for Python 3
Home-page: https://github.com/xdesai96/tlh-legacy
Download-URL: https://github.com/xdesai96/tlh-legacy/releases
Author: xdesai96
Author-email: xdesai@proton.me
License: MIT
Keywords: telegram api chat client library messaging mtproto
Classifier: Development Status :: 5 - Production/Stable
Classifier: Intended Audience :: Developers
Classifier: Topic :: Communications :: Chat
Classifier: License :: OSI Approved :: MIT License
Classifier: Programming Language :: Python :: 3
Classifier: Programming Language :: Python :: 3.5
Classifier: Programming Language :: Python :: 3.6
Classifier: Programming Language :: Python :: 3.7
Classifier: Programming Language :: Python :: 3.8
Requires-Python: >=3.8
License-File: LICENSE
Requires-Dist: pyaes
Requires-Dist: rsa
Provides-Extra: cryptg
Requires-Dist: cryptg; extra == "cryptg"
Dynamic: author
Dynamic: author-email
Dynamic: classifier
Dynamic: description
Dynamic: download-url
Dynamic: home-page
Dynamic: keywords
Dynamic: license
Dynamic: license-file
Dynamic: provides-extra
Dynamic: requires-dist
Dynamic: requires-python
Dynamic: summary
